{
  "hash": "c1e04e0d",
  "configHash": "e91eedf8",
  "lockfileHash": "492c9556",
  "browserHash": "5d20f64e",
  "optimized": {
    "vue": {
      "src": "../../../node_modules/vue/dist/vue.runtime.esm-bundler.js",
      "file": "vue.js",
      "fileHash": "1762097c",
      "needsInterop": false
    },
    "vitepress > @vue/devtools-api": {
      "src": "../../../node_modules/@vue/devtools-api/dist/index.js",
      "file": "vitepress___@vue_devtools-api.js",
      "fileHash": "e14239c1",
      "needsInterop": false
    },
    "vitepress > @vueuse/core": {
      "src": "../../../node_modules/@vueuse/core/index.mjs",
      "file": "vitepress___@vueuse_core.js",
      "fileHash": "fe61cb6d",
      "needsInterop": false
    }
  },
  "chunks": {
    "chunk-6WQ4PVLM": {
      "file": "chunk-6WQ4PVLM.js"
    }
  }
}